anticipy/__init__.py
anticipy/app.py
anticipy/forecast.py
anticipy/forecast_models.py
anticipy/forecast_plot.py
anticipy/model_utils.py
anticipy/utils_test.py
benchmarks/__init__.py
benchmarks/benchmarks.py
tests/__init__.py
tests/test_forecast.py
tests/test_forecast_model.py
tests/test_forecast_plot.py
tests/test_model_utils.py
anticipy-0.2.1.dist-info/LICENSE.md
anticipy-0.2.1.dist-info/METADATA
anticipy-0.2.1.dist-info/WHEEL
anticipy-0.2.1.dist-info/entry_points.txt
anticipy-0.2.1.dist-info/top_level.txt
anticipy-0.2.1.dist-info/RECORD
