Metadata-Version: 2.1
Name: anticipy
Version: 0.2.1
Summary: Forecasting tools
Home-page: https://github.com/sky-uk/anticipy
Author: Pedro Capelastegui
Author-email: pedro.capelastegui@sky.uk
License: BSD
Platform: UNKNOWN
Classifier: License :: OSI Approved :: BSD License
License-File: LICENSE.md
Requires-Dist: numpy (>=1.15.1)
Requires-Dist: pandas (>=0.23.0)
Requires-Dist: scipy (>=1.0.0)
Requires-Dist: plotly (>=3.5.0)
Provides-Extra: extras
Requires-Dist: matplotlib (>=2.2.3) ; extra == 'extras'
Requires-Dist: ipython (>=5.8.0) ; extra == 'extras'
Requires-Dist: notebook (>=5.3) ; extra == 'extras'
Requires-Dist: ipywidgets (==7.5) ; extra == 'extras'
